relang/__init__.py
relang/__main__.py
relang/lang.py
relang/model.py
relang/static/script.js
relang/static/style.css
relang/templates/index.html
relang-0.1.dist-info/entry_points.txt
relang-0.1.dist-info/licenses/LICENSE
relang-0.1.dist-info/WHEEL
relang-0.1.dist-info/METADATA
relang-0.1.dist-info/RECORD
