Metadata-Version: 2.4
Name: relang
Version: 0.1
Summary: Relang.
Author-email: Gertjan van Zwieten <git@gjvz.nl>
Requires-Python: >=3.9
Classifier: License :: OSI Approved :: MIT License
License-File: LICENSE
Requires-Dist: flask
Requires-Dist: ctranslate2
Requires-Dist: sentencepiece
